Workbook
Name _Hlk215568700: PSIC!$B$2
Name latent: #REF!
Name latent: '[4]steam table'!$N$5:$Q$102
Name tube_test_press1_12: #REF!

Sheet Detailed PL
C3: PECC2 Innovation Hub, 45 Street No.2, Truong Tho Ward, Thu Duc City, HCMC, Vietnam Tel: +84-28-2221 6468 | Fax: +84-28-2221 0408
B4: DETAILED PACKING LIST
C5: PL No. | D5: ='PL(2_2)'!D5 -> OM4-DE-IS-0008
C6: Dated | D6: ='PL(2_2)'!D6 -> 46157 | J6: * Storage Classification | O6: ** Plant/Equipment/Materials for
C7: Project | D7: ='PL(2_2)'!D7 -> O MON IV THERMAL POWER PLANT | J7: "A" | K7: : Indoor with Air conditioning | P7: HRSG | Q7: STG | R7: GTG | S7: BOP
C8: Referenced DWG No. | J8: "B" | K8: : Indoor without Air conditioning | O8: Unit 1 | P8: B1 | Q8: T1 | R8: G1 | S8: P2
J9: "C" | K9: : Hazardous Material | O9: Unit 2 | P9: B2 | Q9: T2 | R9: G2 | S9: P2
J10: "D" | K10: : Outdoor with waterproofing | O10: Common | P10: B0 | Q10: T0 | R10: G0 | S10: P0
J11: "E" | K11: : Outdoor without waterproofing
B13: SI. No. | C13: Package No. | D13: Description of Goods | F13: Manufacturer | G13: C/O of Goods | H13: Position in price schedule | I13: Quantity | K13: Package Type | L13: Measurement | P13: Net Weight (kg) | Q13: Gross Weight (kg) | R13: Hazardous Material | S13: Storage Classification (*) | T13: Tag No. | U13: Remark (**)
I14: Nos | J14: Unit | L14: Length (cm) | M14: Width (cm) | N14: Height (cm) | O14: Volume (cbm)
B15: 1 | C15: OM4-DE-IS-0008-001 | D15: PVC Bond | E15: 1KG/CAN | F15: SAMSUNG E&L | G15: Republic of Korea | H15: PS 1.1, Ⅴ, 11 | I15: 260 | J15: EA | P15: =W15*I15 -> 260 | W15: 1
B16: Sub-Total | I16: =SUM(I15) -> 260 | K16: Wodden | L16: 100 | M16: 100 | N16: 140 | O16: =(L16*M16*N16)/10^6 -> 1.4 | P16: =P15 -> 260 | Q16: =P16+150 -> 410 | R16: Y | S16: D | U16: P0
B17: 2 | C17: OM4-DE-IS-0008-002 | D17: PVC Bond | E17: 1KG/CAN | F17: SAMSUNG E&L | G17: Republic of Korea | H17: PS 1.1, Ⅴ, 11 | I17: 240 | J17: EA | P17: =W17*I17 -> 240 | W17: 1
B18: Sub-Total | I18: =SUM(I17) -> 240 | K18: Wodden | L18: 100 | M18: 100 | N18: 110 | O18: =(L18*M18*N18)/10^6 -> 1.1 | P18: =P17 -> 240 | Q18: =P18+150 -> 390 | R18: Y | S18: D | U18: P0
B19: 3 | C19: OM4-DE-IS-0008-003 | D19: PVC Bond | E19: 1KG/CAN | F19: SAMSUNG E&L | G19: Republic of Korea | H19: PS 1.1, Ⅴ, 11 | I19: 100 | J19: EA | P19: =W19*I19 -> 100 | W19: 1
B20: Sub-Total | I20: =SUM(I19) -> 100 | K20: Wodden | L20: 100 | M20: 100 | N20: 70 | O20: =(L20*M20*N20)/10^6 -> 0.7 | P20: =P19 -> 100 | Q20: =P20+150 -> 250 | R20: Y | S20: D | U20: P0
B21: Grand-Total | O21: =SUM(O15:O20) -> 3.2 | P21: =SUM(P16,P18,P20,) -> 600 | Q21: =SUM(Q15:Q20) -> 1050

Sheet Commercial Invoice
B3: PECC2 Innovation Hub, 45 Street No.2, Truong Tho Ward, Thu Duc City, HCMC, Vietnam Tel: +84-28-2221 6468 | Fax: +84-28-2221 0408
A4: COMMERCIAL INVOICE
A5: SHIPPER: | G5: INVOICE NO. : | H5: OM4-DE-IS-0008
B6: Doosan Enerbility Co., Ltd. 22 DoosanVolvo-ro, Seongsan-gu, Chang-won-si, Gyeongsangnam-do 51711, Republic of Korea | G6: DATE: | H6: 46157
G7: CONTRACT NO. | H7: 06/2025/HĐ-PVN/OM4-06
G8: DATE: | H8: 45814
A9: CONSIGNEE : | G9: SHIPPING MARK
B10: Cty Doosan Enerbility Co.,Ltd HQ-Nha thau TH CV thuoc Goi thau so OM4-EPC-HHO-06 cho NMND O Mon IV Thoi Loi Area, Phuoc Thoi Ward, Can Tho City, Vietnam T : (+84) 367 566 167 F : (+84 243) 624 8485 | G10: O MON IV THERMAL POWER PLANT
A13: NOTIFY PARTY :
B14: Cty Doosan Enerbility Co.,Ltd HQ-Nha thau TH CV thuoc Goi thau so OM4-EPC-HHO-06 cho NMND O Mon IV Thoi Loi Area, Phươc Thoi Ward, Can Tho City, Vietnam T : (+84) 367 566 167 F : (+84 243) 624 8485 BRANCH OF KWANGJIN VIET NAM IN DUNG QUAT Co.,Ltd Dung Quat Economic Zone, Van Tuong Commune, Quang Ngai Province, Vietnam T : (+84) 28 3825 6330 Attn: Mr. Phuoc / Email: phuoc@kjtc.co.kr
G15: SHIPMENT NO. : | H15: =H5 -> OM4-DE-IS-0008
G17: TERM OF DELIVERY : | H17: CIF, Ho Chi Minh City Port, Vietnam
A18: VESSEL NAME : | C18: ETD :
B19: HMM HARMONY 0022S | D19: 46169 | G19: QUALITY | H19: 100% BRAND NEW
A20: PORT OF LOADING : | C20: PORT OF DISCHARGE : | G20: PAYMENT TERMS: | H20: T/T
B21: Busan International Port, Korea | D21: Ho Chi Minh City Port, Vietnam
A22: BILL OF LADING/ AIRWAY BILL NO. : | C22: B/L DATE :
A24: FINAL DESTINATION :
B25: O MON IV THERMAL POWER PLANT
B26: Address: O Mon Power Complex at Phuoc Thoi wards, Can Tho city
A27: COMMODITY/DESCRIPTION OF GOODS | H27: UNIT | I27: QUANTITY | J27: UNIT PRICE (USD) | K27: AMOUNT (USD)
B28: PLANT/ EQUIPMENT AND MATERIALS FOR O MON IV THERMAL POWER PLANT (Contract No. OM4-PO-DE-001)
B30: Conduit & Accessories included I&C Conduit (PVC Bond) | H30: EA | I30: =SUM('Break Down CI'!F9:F11) -> 600 | K30: ='Break Down CI'!L12 -> 2741.29
B33: Number of packages: | D33: 3 | E33: PKGS
B38: TOTAL AMOUNT AT THIS SHIPMENT : | K38: =SUM(K30:K32) -> 2741.29
G45: Signed by
H46: Jinho. Lee / Deputy Project Director

Sheet Break Down CI
B5: ='Commercial Invoice'!G5 -> INVOICE NO. : | C5: ='Commercial Invoice'!H5 -> OM4-DE-IS-0008 | K5: DATE : | M5: ='Commercial Invoice'!H6 -> 46157
A7: SI. No. | B7: Package No. | C7: COMMODITY/DESCRIPTION OF GOODS | D7: C/O of Goods | E7: POSITION IN PRICE SCHEDULE | F7: Quantity | H7: Package Type | I7: NET WEIGHT (KG) | J7: GROSS WEIGHT (KG) | K7: UNIT PRICE (USD) | L7: AMOUNT (USD) | M7: Remark (**)
F8: Nos | G8: Unit | O8: HS CODE
A9: 1 | B9: OM4-DE-IS-0008-001 | C9: PVC Bond 1KG/CAN | D9: Republic of Korea | E9: PS 1.1, Ⅴ, 11 | F9: ='PL(2_2)'!F15 -> 260 | G9: ='PL(2_2)'!G16 -> EA | H9: Wooden | I9: ='PL(2_2)'!M15 -> 260 | J9: ='PL(2_2)'!N15 -> 410 | K9: 4.56 | L9: =K9*F9 -> 1185.6 | M9: P0 | O9: 3506.10-9000
A10: 2 | B10: OM4-DE-IS-0008-002 | C10: PVC Bond 1KG/CAN | D10: Republic of Korea | E10: PS 1.1, Ⅴ, 11 | F10: ='PL(2_2)'!F16 -> 240 | G10: EA | H10: Wooden | I10: ='PL(2_2)'!M16 -> 240 | J10: ='PL(2_2)'!N16 -> 390 | K10: 4.56 | L10: =K10*F10 -> 1094.4 | M10: P0 | O10: 3506.10-9000
A11: 3 | B11: OM4-DE-IS-0008-003 | C11: PVC Bond 1KG/CAN | D11: Republic of Korea | E11: PS 1.1, Ⅴ, 11 | F11: ='PL(2_2)'!F17 -> 100 | G11: EA | H11: Wooden | I11: ='PL(2_2)'!M17 -> 100 | J11: ='PL(2_2)'!N17 -> 250 | K11: 4.6129 | L11: =K11*F11 -> 461.29 | M11: P0 | O11: 3506.10-9000
H12: TOTAL AMOUNT AT THIS SHIPMENT | L12: =SUM(L9:L11) -> 2741.29
O14: 2741.29
L17: =L9-O18 -> 1185.6 | M17: =ROUND(L17/F9,2) -> 4.56 | O17: =L12-O14 -> 0
L18: =L10-O18 -> 1094.4 | M18: =ROUND(L18/F10,2) -> 4.56 | O18: =O17/3 -> 0
L19: =L11-O18 -> 461.29 | M19: =ROUND(L19/F11,2) -> 4.61
O21: =L11-O17 -> 461.29
O24: =O14/600 -> 4.5688167
N27: =L11/F11 -> 4.6129
O28: =ROUND(O24,2) -> 4.57

Sheet Packing List (1_2)
B3: PECC2 Innovation Hub, 45 Street No.2, Truong Tho Ward, Thu Duc City, HCMC, Vietnam Tel: +84-28-2221 6468 | Fax: +84-28-2221 0408
A4: PACKING LIST(1/2)
A5: SHIPPER: | G5: P/L No. | H5: OM4-DE-IS-0008
B6: Doosan Enerbility Co., Ltd. 22 DoosanVolvo-ro, Seongsan-gu, Chang-won-si, Gyeongsangnam-do 51711, Republic of Korea | G6: DATE: | H6: ='Commercial Invoice'!H6 -> 46157
G7: CONTRACT NO. | H7: 06/2025/HĐ-PVN/OM4-06
G8: DATE: | H8: ='Commercial Invoice'!H8 -> 45814
A9: CONSIGNEE : | G9: =[6]CI!G9 -> SHIPPING MARK
B10: Cty Doosan Enerbility Co.,Ltd HQ-Nha thau TH CV thuoc Goi thau so OM4-EPC-HHO-06 cho NMND O Mon IV Thoi Loi Area, Phuoc Thoi Ward, Can Tho City, Vietnam T : (+84) 367 566 167 F : (+84 243) 624 8485 | G10: O MON IV THERMAL POWER PLANT
A13: NOTIFY PARTY :
B14: Cty Doosan Enerbility Co.,Ltd HQ-Nha thau TH CV thuoc Goi thau so OM4-EPC-HHO-06 cho NMND O Mon IV Thoi Loi Area, Phươc Thoi Ward, Can Tho City, Vietnam T : (+84) 367 566 167 F : (+84 243) 624 8485 BRANCH OF KWANGJIN VIET NAM IN DUNG QUAT Co.,Ltd Dung Quat Economic Zone, Van Tuong Commune, Quang Ngai Province, Vietnam T : (+84) 28 3825 6330 Attn: Mr. Phuoc / Email: phuoc@kjtc.co.kr
G15: SHIPMENT NO. : | H15: =H5 -> OM4-DE-IS-0008
G17: TERM OF DELIVERY : | H17: CIF, Ho Chi Minh City Port, Vietnam
A18: VESSEL NAME : | C18: ETD :
B19: HMM HARMONY 0022S | D19: 46169 | G19: QUALITY | H19: 100% BRAND NEW
A20: PORT OF LOADING : | C20: PORT OF DISCHARGE :
B21: Busan International Port, Korea | D21: Ho Chi Minh City Port, Vietnam
A22: BILL OF LADING/ AIRWAY BILL NO. : | C22: B/L DATE :
A24: FINAL DESTINATION :
B25: O MON IV THERMAL POWER PLANT
B26: Address: O Mon Power Complex at Phuoc Thoi wards, Can Tho city
A27: COMMODITY/DESCRIPTION OF GOODS | G27: UNIT | H27: QUANTITY | I27: NET WEIGHT (KG) | J27: GROSS WEIGHT (KG) | K27: MEASUREMENT (CBM)
B28: PLANT/ EQUIPMENT AND MATERIALS FOR O MON IV THERMAL POWER PLANT (Contract No. OM4-PO-DE-001)
A30: Conduit & Accessories included I&C Conduit (PVC Bond)
G31: EA | H31: 260 | I31: ='PL(2_2)'!M15 -> 260 | J31: ='PL(2_2)'!N15 -> 410 | K31: ='PL(2_2)'!L15 -> 1.4
G32: EA | H32: 240 | I32: ='PL(2_2)'!M16 -> 240 | J32: ='PL(2_2)'!N16 -> 390 | K32: ='PL(2_2)'!L16 -> 1.1
G33: EA | H33: 100 | I33: ='PL(2_2)'!M17 -> 100 | J33: ='PL(2_2)'!N17 -> 250 | K33: ='PL(2_2)'!L17 -> 0.7
B37: Number of packages: | D37: 3 | E37: PKGS
G41: TOTAL | I41: =SUM(I28:I40) -> 600 | J41: =SUM(J28:J40) -> 1050 | K41: =SUM(K28:K40) -> 3.2
G49: Signed by
H50: Jinho. Lee / Deputy Project Director

Sheet PL(2_2)
C3: PECC2 Innovation Hub, 45 Street No.2, Truong Tho Ward, Thu Duc City, HCMC, Vietnam Tel: +84-28-2221 6468 | Fax: +84-28-2221 0408
B4: PACKING LIST(2/2)
C5: P/L No. | D5: ='Packing List (1_2)'!H5 -> OM4-DE-IS-0008
C6: Dated | D6: ='Packing List (1_2)'!H6 -> 46157 | I6: * Storage Classification | N6: ** Plant/Equipment/Materials for
C7: Project | D7: O MON IV THERMAL POWER PLANT | I7: "A" | J7: : Indoor with Air conditioning | O7: HRSG | P7: STG | Q7: GTG | R7: BOP
I8: "B" | J8: : Indoor without Air conditioning | N8: Unit 1 | O8: B1 | P8: T1 | Q8: G1 | R8: P2
I9: "C" | J9: : Hazardous Material | N9: Unit 2 | O9: B2 | P9: T2 | Q9: G2 | R9: P2
I10: "D" | J10: : Outdoor with waterproofing | N10: Common | O10: B0 | P10: T0 | Q10: G0 | R10: P0
I11: "E" | J11: : Outdoor without waterproofing
B13: SI. No. | C13: Package No. | D13: Description of Goods | E13: Position in price schedule | F13: Quantity | H13: Package Type | I13: Measurement | M13: Net Weight (kg) | N13: Gross Weight (kg) | O13: Hazardous Material | P13: COG Marked (Y/N) | Q13: Sling Point Marked (Y/N) | R13: Handle with care Marked (Y/N) | S13: Storage Classification (*) | T13: Remark (**)
F14: Nos | G14: Unit | I14: Length (cm) | J14: Width (cm) | K14: Height (cm) | L14: Volume (cbm)
B15: 1 | C15: ='Detailed PL'!C15 -> OM4-DE-IS-0008-001 | D15: PVC Bond | F15: =SUM('Detailed PL'!I16) -> 260 | G15: EA | H15: ='Detailed PL'!K16 -> Wodden | I15: ='Detailed PL'!L16 -> 100 | J15: ='Detailed PL'!M16 -> 100 | K15: ='Detailed PL'!N16 -> 140 | L15: ='Detailed PL'!O16 -> 1.4 | M15: ='Detailed PL'!P16 -> 260 | N15: ='Detailed PL'!Q16 -> 410 | O15: ='Detailed PL'!R16 -> Y | P15: Y | Q15: Y | R15: N | S15: ='Detailed PL'!S16 -> D | T15: ='Detailed PL'!U16 -> P0
B16: 2 | C16: ='Detailed PL'!C17 -> OM4-DE-IS-0008-002 | D16: PVC Bond | F16: =SUM('Detailed PL'!I18) -> 240 | G16: EA | H16: ='Detailed PL'!K18 -> Wodden | I16: ='Detailed PL'!L18 -> 100 | J16: ='Detailed PL'!M18 -> 100 | K16: ='Detailed PL'!N18 -> 110 | L16: ='Detailed PL'!O18 -> 1.1 | M16: ='Detailed PL'!P18 -> 240 | N16: ='Detailed PL'!Q18 -> 390 | O16: ='Detailed PL'!R18 -> Y | P16: Y | Q16: Y | R16: N | S16: ='Detailed PL'!S18 -> D | T16: ='Detailed PL'!U18 -> P0
B17: 3 | C17: ='Detailed PL'!C19 -> OM4-DE-IS-0008-003 | D17: PVC Bond | F17: =SUM('Detailed PL'!I20) -> 100 | G17: EA | H17: ='Detailed PL'!K20 -> Wodden | I17: ='Detailed PL'!L20 -> 100 | J17: ='Detailed PL'!M20 -> 100 | K17: ='Detailed PL'!N20 -> 70 | L17: ='Detailed PL'!O20 -> 0.7 | M17: ='Detailed PL'!P20 -> 100 | N17: ='Detailed PL'!Q20 -> 250 | O17: ='Detailed PL'!R20 -> Y | P17: Y | Q17: Y | R17: N | S17: ='Detailed PL'!S20 -> D | T17: ='Detailed PL'!U20 -> P0
B18: Grand Total | L18: =SUM(L15:L17) -> 3.2 | M18: =SUM(M15:M17) -> 600 | N18: =SUM(N15:N17) -> 1050

Sheet SHIPPING MARK (001)
A1: SHIPPING MARK
A2: O MON IV THERMAL POWER PLANT
A3: =[6]CI!B26 -> Address: O Mon Power Complex at Phuoc Thoi wards, O Mon district, Can Tho city
A5: SHIPPER | B5: : | C5: Doosan Enerbility Co., Ltd.
A6: ADDRESS | B6: : | C6: 22 DoosanVolvo-ro, Seongsan-gu, Chang-won-si, Gyeongsangnam-do 51711, Republic of Korea
A7: CONSIGNEE | B7: : | C7: Cty Doosan Enerbility Co.,Ltd HQ-Nha thau TH CV thuoc Goi thau so OM4-EPC-HHO-06 cho NMND O Mon IV Thoi Loi Area, Phuoc Thoi Ward, Can Tho City, Vietnam T : (+84) 367 566 167 F : (+84 243) 624 8485
A8: NOTIFY PARTY | B8: : | C8: Cty Doosan Enerbility Co.,Ltd HQ-Nha thau TH CV thuoc Goi thau so OM4-EPC-HHO-06 cho NMND O Mon IV Thoi Loi Area, Phươc Thoi Ward, Can Tho City, Vietnam T : (+84) 367 566 167 F : (+84 243) 624 8485 BRANCH OF KWANGJIN VIET NAM IN DUNG QUAT Co.,Ltd Dung Quat Economic Zone, Van Tuong Commune, Quang Ngai Province, Vietnam T : (+84) 28 3825 6330 Attn: Mr. Phuoc / Email: phuoc@kjtc.co.kr
A12: CONTRACT NO. | B12: : | C12: 06/2025/HĐ-PVN/OM4-06
A13: SHIPMENT NO. | B13: : | C13: OM4-DE-IS-0008
A14: EQUIPMENT DESCRIPTION | B14: : | C14: =[6]CI!B28 -> PLANT/ EQUIPMENT AND MATERIALS FOR O MON IV THERMAL
A15: DESCRIPTION OF GOODS | B15: : | C15: ='PL(2_2)'!D15 -> PVC Bond | L15: PL(2_2) Sheet 내 내용 반영 필요
A16: CONSIGNOR. | B16: : | C16: SAMSUNG E&L
A17: PACKAGE NO. | B17: : | C17: ='PL(2_2)'!C15 -> OM4-DE-IS-0008-001
A18: NET WEIGHT | B18: : | C18: ='PL(2_2)'!M15 -> 260 | D18: KG
A19: GROSS WEIGHT | B19: : | C19: ='PL(2_2)'!N15 -> 410 | D19: KG
A20: - MEASUREMENT | B20: : | C20: ='PL(2_2)'!I15 -> 100 | D20: cm(L) X | E20: ='PL(2_2)'!J15 -> 100 | F20: cm (W) X | G20: ='PL(2_2)'!K15 -> 140 | H20: cm (H) | I20: ='PL(2_2)'!L15 -> 1.4 | J20: CBM
A21: LOADING PORT | B21: : | C21: ='Packing List (1_2)'!B21 -> Busan International Port, Korea
A22: PORT OF DESTINATION | B22: : | C22: Ho Chi Minh City Port, Vietnam
A23: COUNTRY OF ORIGIN | B23: : | C23: Republic of Korea
A24: QUALITY | B24: : | C24: 100% BRAND NEW

Sheet SHIPPING MARK (002)
A1: SHIPPING MARK
A2: O MON IV THERMAL POWER PLANT
A3: =[6]CI!B26 -> Address: O Mon Power Complex at Phuoc Thoi wards, O Mon district, Can Tho city
A5: SHIPPER | B5: : | C5: Doosan Enerbility Co., Ltd.
A6: ADDRESS | B6: : | C6: 22 DoosanVolvo-ro, Seongsan-gu, Chang-won-si, Gyeongsangnam-do 51711, Republic of Korea
A7: CONSIGNEE | B7: : | C7: Cty Doosan Enerbility Co.,Ltd HQ-Nha thau TH CV thuoc Goi thau so OM4-EPC-HHO-06 cho NMND O Mon IV Thoi Loi Area, Phuoc Thoi Ward, Can Tho City, Vietnam T : (+84) 367 566 167 F : (+84 243) 624 8485
A8: NOTIFY PARTY | B8: : | C8: Cty Doosan Enerbility Co.,Ltd HQ-Nha thau TH CV thuoc Goi thau so OM4-EPC-HHO-06 cho NMND O Mon IV Thoi Loi Area, Phươc Thoi Ward, Can Tho City, Vietnam T : (+84) 367 566 167 F : (+84 243) 624 8485 BRANCH OF KWANGJIN VIET NAM IN DUNG QUAT Co.,Ltd Dung Quat Economic Zone, Van Tuong Commune, Quang Ngai Province, Vietnam T : (+84) 28 3825 6330 Attn: Mr. Phuoc / Email: phuoc@kjtc.co.kr
A12: CONTRACT NO. | B12: : | C12: 06/2025/HĐ-PVN/OM4-06
A13: SHIPMENT NO. | B13: : | C13: OM4-DE-IS-0008
A14: EQUIPMENT DESCRIPTION | B14: : | C14: =[6]CI!B28 -> PLANT/ EQUIPMENT AND MATERIALS FOR O MON IV THERMAL
A15: DESCRIPTION OF GOODS | B15: : | C15: ='PL(2_2)'!D16 -> PVC Bond | L15: PL(2_2) Sheet 내 내용 반영 필요
A16: CONSIGNOR. | B16: : | C16: SAMSUNG E&L
A17: PACKAGE NO. | B17: : | C17: ='PL(2_2)'!C16 -> OM4-DE-IS-0008-002
A18: NET WEIGHT | B18: : | C18: ='PL(2_2)'!M16 -> 240 | D18: KG
A19: GROSS WEIGHT | B19: : | C19: ='PL(2_2)'!N16 -> 390 | D19: KG
A20: - MEASUREMENT | B20: : | C20: ='PL(2_2)'!I16 -> 100 | D20: cm(L) X | E20: ='PL(2_2)'!J16 -> 100 | F20: cm (W) X | G20: ='PL(2_2)'!K16 -> 110 | H20: cm (H) | I20: ='PL(2_2)'!L16 -> 1.1 | J20: CBM
A21: LOADING PORT | B21: : | C21: ='Packing List (1_2)'!B21 -> Busan International Port, Korea
A22: PORT OF DESTINATION | B22: : | C22: Ho Chi Minh City Port, Vietnam
A23: COUNTRY OF ORIGIN | B23: : | C23: Republic of Korea
A24: QUALITY | B24: : | C24: 100% BRAND NEW

Sheet SHIPPING MARK (003)
A1: SHIPPING MARK
A2: O MON IV THERMAL POWER PLANT
A3: =[6]CI!B26 -> Address: O Mon Power Complex at Phuoc Thoi wards, O Mon district, Can Tho city
A5: SHIPPER | B5: : | C5: Doosan Enerbility Co., Ltd.
A6: ADDRESS | B6: : | C6: 22 DoosanVolvo-ro, Seongsan-gu, Chang-won-si, Gyeongsangnam-do 51711, Republic of Korea
A7: CONSIGNEE | B7: : | C7: Cty Doosan Enerbility Co.,Ltd HQ-Nha thau TH CV thuoc Goi thau so OM4-EPC-HHO-06 cho NMND O Mon IV Thoi Loi Area, Phuoc Thoi Ward, Can Tho City, Vietnam T : (+84) 367 566 167 F : (+84 243) 624 8485
A8: NOTIFY PARTY | B8: : | C8: Cty Doosan Enerbility Co.,Ltd HQ-Nha thau TH CV thuoc Goi thau so OM4-EPC-HHO-06 cho NMND O Mon IV Thoi Loi Area, Phươc Thoi Ward, Can Tho City, Vietnam T : (+84) 367 566 167 F : (+84 243) 624 8485 BRANCH OF KWANGJIN VIET NAM IN DUNG QUAT Co.,Ltd Dung Quat Economic Zone, Van Tuong Commune, Quang Ngai Province, Vietnam T : (+84) 28 3825 6330 Attn: Mr. Phuoc / Email: phuoc@kjtc.co.kr
A12: CONTRACT NO. | B12: : | C12: 06/2025/HĐ-PVN/OM4-06
A13: SHIPMENT NO. | B13: : | C13: OM4-DE-IS-0008
A14: EQUIPMENT DESCRIPTION | B14: : | C14: =[6]CI!B28 -> PLANT/ EQUIPMENT AND MATERIALS FOR O MON IV THERMAL
A15: DESCRIPTION OF GOODS | B15: : | C15: ='PL(2_2)'!D17 -> PVC Bond | L15: PL(2_2) Sheet 내 내용 반영 필요
A16: CONSIGNOR. | B16: : | C16: SAMSUNG E&L
A17: PACKAGE NO. | B17: : | C17: ='PL(2_2)'!C17 -> OM4-DE-IS-0008-003
A18: NET WEIGHT | B18: : | C18: ='PL(2_2)'!M17 -> 100 | D18: KG
A19: GROSS WEIGHT | B19: : | C19: ='PL(2_2)'!N17 -> 250 | D19: KG
A20: - MEASUREMENT | B20: : | C20: ='PL(2_2)'!I17 -> 100 | D20: cm(L) X | E20: ='PL(2_2)'!J17 -> 100 | F20: cm (W) X | G20: ='PL(2_2)'!K17 -> 70 | H20: cm (H) | I20: ='PL(2_2)'!L17 -> 0.7 | J20: CBM
A21: LOADING PORT | B21: : | C21: ='Packing List (1_2)'!B21 -> Busan International Port, Korea
A22: PORT OF DESTINATION | B22: : | C22: Ho Chi Minh City Port, Vietnam
A23: COUNTRY OF ORIGIN | B23: : | C23: Republic of Korea
A24: QUALITY | B24: : | C24: 100% BRAND NEW

Sheet Technical Description
A6: Technical Description
A7: Invoice no. | B7: ='Commercial Invoice'!H5 -> OM4-DE-IS-0008
A8: № | B8: Package No. | C8: Description of Goods | D8: Quantity | F8: Photo | H8: Technical specifications
D9: Nos | E9: Unit | F9: Before packing | G9: After packing
A10: 1 | B10: ='PL(2_2)'!C15 -> OM4-DE-IS-0008-001 | C10: ='PL(2_2)'!D15 -> PVC Bond | D10: ='PL(2_2)'!F15 -> 260 | E10: ='PL(2_2)'!G15 -> EA
A11: 2 | B11: ='PL(2_2)'!C16 -> OM4-DE-IS-0008-002 | C11: ='PL(2_2)'!D16 -> PVC Bond | D11: ='PL(2_2)'!F16 -> 240 | E11: ='PL(2_2)'!G16 -> EA
A12: 3 | B12: ='PL(2_2)'!C17 -> OM4-DE-IS-0008-003 | C12: ='PL(2_2)'!D17 -> PVC Bond | D12: ='PL(2_2)'!F17 -> 100 | E12: ='PL(2_2)'!G17 -> EA

Sheet CO

Sheet CQ

Sheet BL
I3: - In the B/L Form, "Freight Prepaid" must be used according to the signed EPC regulations, "Freight payable" cannot be used as the form we are drafting. - According to EPC, the Contractor is required to bear the risks and losses until handover, and must insure all goods during transportation, so remove the content of the complicated limitation regulations below in the B/L Form.

Sheet PSIC
