Workbook
Name _Hlk215568700: PSIC!$B$2
Name latent: #REF!
Name latent: '[4]steam table'!$N$5:$Q$102
Name tube_test_press1_12: #REF!

Sheet Break Down CI
B5: ='Commercial Invoice'!G5 -> INVOICE NO. : | E5: ='Commercial Invoice'!H5 -> OM4-DE-IS-0010 | M5: DATE : | O5: ='Commercial Invoice'!H6 -> 46177
A7: SI. No. | B7: Package No. | C7: Vị trí | D7: Ngày Nhận | E7: COMMODITY/DESCRIPTION OF GOODS | F7: C/O of Goods | G7: POSITION IN PRICE SCHEDULE | H7: Quantity | J7: Package Type | K7: NET WEIGHT (KG) | L7: GROSS WEIGHT (KG) | M7: UNIT PRICE (USD) | N7: AMOUNT (USD) | O7: Remark (**)
H8: Nos | I8: Unit | Q8: HS CODE
A9: 1 | B9: OM4-DE-IS-0010-001 | C9: Office | D9: 46231 | E9: Zinc Primer Paint, 18L | F9: Republic of Korea | G9: PS 1.1, Ⅴ, 11 | H9: ='Detailed PL'!I15 -> 32 | I9: ='Detailed PL'!J15 -> EA | J9: ='Detailed PL'!K16 -> Wooden | K9: ='Detailed PL'!P16 -> 576 | L9: ='Detailed PL'!Q16 -> 726 | M9: 90.67 | N9: 2901.44 | O9: P0 | Q9: 3208.90-9019
A10: 2 | B10: OM4-DE-IS-0010-002 | C10: Office | D10: 46231 | E10: Zinc Primer Paint, 18L | F10: Republic of Korea | G10: PS 1.1, Ⅴ, 11 | H10: ='Detailed PL'!I17 -> 18 | I10: ='Detailed PL'!J17 -> EA | J10: ='Detailed PL'!K18 -> Wooden | K10: ='Detailed PL'!P18 -> 324 | L10: ='Detailed PL'!Q18 -> 474 | M10: 90.68 | N10: 1632.23 | O10: P0 | Q10: 3208.90-9019
J11: TOTAL AMOUNT AT THIS SHIPMENT | N11: =SUM(N9:N10) -> 4533.67
Q12: =N9+P19 -> 5802.88
Q13: =N10+P20 -> 3264.47
N16: =M9*H9 -> 2901.44 | P16: =H9*M9 -> 2901.44
N17: =M10*H10 -> 1632.24 | P17: =H10*M10 -> 1632.24
N18: =SUM(N16:N17) -> 4533.68
P19: =ROUND(P16,2) -> 2901.44
N20: 2901.55 | P20: =ROUND(P17,2) -> 1632.24
N21: 1632.12
N22: 4533.67

Sheet Detailed PL
C3: PECC2 Innovation Hub, 45 Street No.2, Truong Tho Ward, Thu Duc City, HCMC, Vietnam Tel: +84-28-2221 6468 | Fax: +84-28-2221 0408
B4: DETAILED PACKING LIST
C5: PL No. | D5: ='PL(2_2)'!D5 -> OM4-DE-IS-0010
C6: Dated | D6: ='PL(2_2)'!D6 -> 46177 | J6: * Storage Classification | O6: ** Plant/Equipment/Materials for
C7: Project | D7: ='PL(2_2)'!D7 -> O MON IV THERMAL POWER PLANT | J7: "A" | K7: : Indoor with Air conditioning | P7: HRSG | Q7: STG | R7: GTG | S7: BOP
C8: Referenced DWG No. | J8: "B" | K8: : Indoor without Air conditioning | O8: Unit 1 | P8: B1 | Q8: T1 | R8: G1 | S8: P2
J9: "C" | K9: : Hazardous Material | O9: Unit 2 | P9: B2 | Q9: T2 | R9: G2 | S9: P2
J10: "D" | K10: : Outdoor with waterproofing | O10: Common | P10: B0 | Q10: T0 | R10: G0 | S10: P0
J11: "E" | K11: : Outdoor without waterproofing
B13: SI. No. | C13: Package No. | D13: Description of Goods | F13: Manufacturer | G13: C/O of Goods | H13: Position in price schedule | I13: Quantity | K13: Package Type | L13: Measurement | P13: Net Weight (kg) | Q13: Gross Weight (kg) | R13: Hazardous Material | S13: Storage Classification (*) | T13: Tag No. | U13: Remark (**)
I14: Nos | J14: Unit | L14: Length (cm) | M14: Width (cm) | N14: Height (cm) | O14: Volume (cbm)
B15: 1 | C15: OM4-DE-IS-0010-001 | D15: Zinc Primer Paint | E15: 18L | F15: SAMSUNG E&L | G15: Republic of Korea | I15: 32 | J15: EA | P15: 576 | W15: 18
B16: Sub-Total | I16: =SUM(I15) -> 32 | K16: Wooden | L16: 120 | M16: 120 | N16: 110 | O16: =(L16*M16*N16)/10^6 -> 1.584 | P16: 576 | Q16: =P16+150 -> 726 | R16: Y | S16: D | U16: P0
B17: 2 | C17: OM4-DE-IS-0010-002 | D17: Zinc Primer Paint | E17: 18L | F17: SAMSUNG E&L | G17: Republic of Korea | I17: 18 | J17: EA | P17: 324 | W17: 18
B18: Sub-Total | I18: =SUM(I17:I17) -> 18 | K18: Wooden | L18: 120 | M18: 120 | N18: 110 | O18: =(L18*M18*N18)/10^6 -> 1.584 | P18: 324 | Q18: =P18+150 -> 474 | R18: Y | S18: D | U18: P0
B19: Grand-Total | O19: =SUM(O15:O18) -> 3.168 | P19: =SUM(P16,P18) -> 900 | Q19: =SUM(Q15:Q18) -> 1200

Sheet Commercial Invoice
B3: PECC2 Innovation Hub, 45 Street No.2, Truong Tho Ward, Thu Duc City, HCMC, Vietnam Tel: +84-28-2221 6468 | Fax: +84-28-2221 0408
A4: COMMERCIAL INVOICE
A5: SHIPPER: | G5: INVOICE NO. : | H5: OM4-DE-IS-0010
B6: Doosan Enerbility Co., Ltd. 22 DoosanVolvo-ro, Seongsan-gu, Chang-won-si, Gyeongsangnam-do 51711, Republic of Korea | G6: DATE: | H6: 46177
G7: CONTRACT NO. | H7: 06/2025/HĐ-PVN/OM4-06
G8: DATE: | H8: 45814
A9: CONSIGNEE : | G9: SHIPPING MARK
B10: Cty Doosan Enerbility Co.,Ltd HQ-Nha thau TH CV thuoc Goi thau so OM4-EPC-HHO-06 cho NMND O Mon IV Thoi Loi Area, Phuoc Thoi Ward, Can Tho City, Vietnam T : (+84) 367 566 167 F : (+84 243) 624 8485 | G10: O MON IV THERMAL POWER PLANT
A13: NOTIFY PARTY :
B14: Cty Doosan Enerbility Co.,Ltd HQ-Nha thau TH CV thuoc Goi thau so OM4-EPC-HHO-06 cho NMND O Mon IV Thoi Loi Area, Phươc Thoi Ward, Can Tho City, Vietnam T : (+84) 367 566 167 F : (+84 243) 624 8485 BRANCH OF KWANGJIN VIET NAM IN DUNG QUAT Co.,Ltd Dung Quat Economic Zone, Van Tuong Commune, Quang Ngai Province, Vietnam T : (+84) 28 3825 6330 Attn: Mr. Phuoc / Email: phuoc@kjtc.co.kr
G15: SHIPMENT NO. : | H15: =H5 -> OM4-DE-IS-0010
G17: TERM OF DELIVERY : | H17: CIF, Ho Chi Minh City Port, Vietnam
A18: VESSEL NAME : | C18: ETD :
B19: HMM MIRACLE 0020S | D19: 46208 | G19: QUALITY | H19: 100% BRAND NEW
A20: PORT OF LOADING : | C20: PORT OF DISCHARGE : | G20: PAYMENT TERMS: | H20: T/T
B21: Busan International Port, Korea | D21: Ho Chi Minh City Port, Vietnam
A22: BILL OF LADING/ AIRWAY BILL NO. : | C22: B/L DATE :
A24: FINAL DESTINATION :
B25: O MON IV THERMAL POWER PLANT
B26: Address: O Mon Power Complex at Phuoc Thoi wards, Can Tho city
A27: COMMODITY/DESCRIPTION OF GOODS | H27: UNIT | I27: QUANTITY | J27: UNIT PRICE (USD) | K27: AMOUNT (USD)
B28: PLANT/ EQUIPMENT AND MATERIALS FOR O MON IV THERMAL POWER PLANT (Contract No. OM4-PO-DE-001)
B30: Conduit & Accessories included I&C Conduit (Zinc Primer Paint) | H30: EA | I30: ='Packing List (1_2)'!H31 -> 32 | J30: =ROUND(K30/I30,2) -> 90.67 | K30: ='Break Down CI'!N9 -> 2901.44 | M30: FOB (물품가액)
H31: EA | I31: ='Packing List (1_2)'!H32 -> 18 | J31: =ROUND(K31/I31,2) -> 90.68 | K31: ='Break Down CI'!N10 -> 1632.23
B33: Number of packages: | D33: 2 | E33: PKGS | M33: Freight | N33: 853
M34: Insurance | N34: =K30*110%*0.1045% -> 3.3352053
B38: TOTAL AMOUNT AT THIS SHIPMENT : | K38: =SUM(K30:K33) -> 4533.67
G45: Signed by
H46: Jinho. Lee / Deputy Project Director

Sheet Packing List (1_2)
B3: PECC2 Innovation Hub, 45 Street No.2, Truong Tho Ward, Thu Duc City, HCMC, Vietnam Tel: +84-28-2221 6468 | Fax: +84-28-2221 0408
A4: PACKING LIST(1/2)
A5: SHIPPER: | G5: P/L No. | H5: OM4-DE-IS-0010
B6: Doosan Enerbility Co., Ltd. 22 DoosanVolvo-ro, Seongsan-gu, Chang-won-si, Gyeongsangnam-do 51711, Republic of Korea | G6: DATE: | H6: ='Commercial Invoice'!H6 -> 46177
G7: CONTRACT NO. | H7: 06/2025/HĐ-PVN/OM4-06
G8: DATE: | H8: ='Commercial Invoice'!H8 -> 45814
A9: CONSIGNEE : | G9: =[6]CI!G9 -> SHIPPING MARK
B10: Cty Doosan Enerbility Co.,Ltd HQ-Nha thau TH CV thuoc Goi thau so OM4-EPC-HHO-06 cho NMND O Mon IV Thoi Loi Area, Phuoc Thoi Ward, Can Tho City, Vietnam T : (+84) 367 566 167 F : (+84 243) 624 8485 | G10: O MON IV THERMAL POWER PLANT
A13: NOTIFY PARTY :
B14: Cty Doosan Enerbility Co.,Ltd HQ-Nha thau TH CV thuoc Goi thau so OM4-EPC-HHO-06 cho NMND O Mon IV Thoi Loi Area, Phươc Thoi Ward, Can Tho City, Vietnam T : (+84) 367 566 167 F : (+84 243) 624 8485 BRANCH OF KWANGJIN VIET NAM IN DUNG QUAT Co.,Ltd Dung Quat Economic Zone, Van Tuong Commune, Quang Ngai Province, Vietnam T : (+84) 28 3825 6330 Attn: Mr. Phuoc / Email: phuoc@kjtc.co.kr
G15: SHIPMENT NO. : | H15: =H5 -> OM4-DE-IS-0010
G17: TERM OF DELIVERY : | H17: CIF, Ho Chi Minh City Port, Vietnam
A18: VESSEL NAME : | C18: ETD :
B19: HMM MIRACLE 0020S | D19: 46208 | G19: QUALITY | H19: 100% BRAND NEW
A20: PORT OF LOADING : | C20: PORT OF DISCHARGE :
B21: Busan International Port, Korea | D21: Ho Chi Minh City Port, Vietnam
A22: BILL OF LADING/ AIRWAY BILL NO. : | C22: B/L DATE :
A24: FINAL DESTINATION :
B25: O MON IV THERMAL POWER PLANT
B26: Address: O Mon Power Complex at Phuoc Thoi wards, Can Tho city
A27: COMMODITY/DESCRIPTION OF GOODS | G27: UNIT | H27: QUANTITY | I27: NET WEIGHT (KG) | J27: GROSS WEIGHT (KG) | K27: MEASUREMENT (CBM)
B28: PLANT/ EQUIPMENT AND MATERIALS FOR O MON IV THERMAL POWER PLANT (Contract No. OM4-PO-DE-001)
A30: Conduit & Accessories included I&C Conduit (Zinc Primer Paint)
G31: EA | H31: ='PL(2_2)'!F15 -> 32 | I31: ='PL(2_2)'!M15 -> 576 | J31: ='PL(2_2)'!N15 -> 726 | K31: ='PL(2_2)'!L15 -> 1.584
G32: EA | H32: ='PL(2_2)'!F16 -> 18 | I32: ='PL(2_2)'!M16 -> 324 | J32: ='PL(2_2)'!N16 -> 474 | K32: ='PL(2_2)'!L16 -> 1.584
B34: Number of packages: | D34: 2 | E34: PKGS
G38: TOTAL | I38: =SUM(I28:I37) -> 900 | J38: =SUM(J28:J37) -> 1200 | K38: =SUM(K28:K37) -> 3.168
G46: Signed by
H47: Jinho. Lee / Deputy Project Director

Sheet PL(2_2)
C3: PECC2 Innovation Hub, 45 Street No.2, Truong Tho Ward, Thu Duc City, HCMC, Vietnam Tel: +84-28-2221 6468 | Fax: +84-28-2221 0408
B4: PACKING LIST(2/2)
C5: P/L No. | D5: ='Packing List (1_2)'!H5 -> OM4-DE-IS-0010
C6: Dated | D6: ='Packing List (1_2)'!H6 -> 46177 | I6: * Storage Classification | N6: ** Plant/Equipment/Materials for
C7: Project | D7: O MON IV THERMAL POWER PLANT | I7: "A" | J7: : Indoor with Air conditioning | O7: HRSG | P7: STG | Q7: GTG | R7: BOP
I8: "B" | J8: : Indoor without Air conditioning | N8: Unit 1 | O8: B1 | P8: T1 | Q8: G1 | R8: P2
I9: "C" | J9: : Hazardous Material | N9: Unit 2 | O9: B2 | P9: T2 | Q9: G2 | R9: P2
I10: "D" | J10: : Outdoor with waterproofing | N10: Common | O10: B0 | P10: T0 | Q10: G0 | R10: P0
I11: "E" | J11: : Outdoor without waterproofing
B13: SI. No. | C13: Package No. | D13: Description of Goods | E13: Position in price schedule | F13: Quantity | H13: Package Type | I13: Measurement | M13: Net Weight (kg) | N13: Gross Weight (kg) | O13: Hazardous Material | P13: COG Marked (Y/N) | Q13: Sling Point Marked (Y/N) | R13: Handle with care Marked (Y/N) | S13: Storage Classification (*) | T13: Remark (**)
F14: Nos | G14: Unit | I14: Length (cm) | J14: Width (cm) | K14: Height (cm) | L14: Volume (cbm)
B15: 1 | C15: ='Detailed PL'!C15 -> OM4-DE-IS-0010-001 | D15: Zinc Primer Paint | F15: =SUM('Detailed PL'!I16) -> 32 | G15: EA | H15: ='Detailed PL'!K16 -> Wooden | I15: ='Detailed PL'!L16 -> 120 | J15: ='Detailed PL'!M16 -> 120 | K15: ='Detailed PL'!N16 -> 110 | L15: ='Detailed PL'!O16 -> 1.584 | M15: ='Detailed PL'!P16 -> 576 | N15: ='Detailed PL'!Q16 -> 726 | O15: Y | P15: Y | Q15: Y | R15: N | S15: ='Detailed PL'!S16 -> D | T15: ='Detailed PL'!U16 -> P0
B16: 2 | C16: ='Detailed PL'!C17 -> OM4-DE-IS-0010-002 | D16: Zinc Primer Paint, Sealant | F16: =SUM('Detailed PL'!I18) -> 18 | G16: EA | H16: ='Detailed PL'!K18 -> Wooden | I16: ='Detailed PL'!L18 -> 120 | J16: ='Detailed PL'!M18 -> 120 | K16: ='Detailed PL'!N18 -> 110 | L16: ='Detailed PL'!O18 -> 1.584 | M16: ='Detailed PL'!P18 -> 324 | N16: ='Detailed PL'!Q18 -> 474 | O16: Y | P16: Y | Q16: Y | R16: N | S16: ='Detailed PL'!S18 -> D | T16: ='Detailed PL'!U18 -> P0
B17: Grand Total | L17: =SUM(L15:L16) -> 3.168 | M17: =SUM(M15:M16) -> 900 | N17: =SUM(N15:N16) -> 1200

Sheet SHIPPING MARK (001)
A1: SHIPPING MARK
A2: O MON IV THERMAL POWER PLANT
A3: =[6]CI!B26 -> Address: O Mon Power Complex at Phuoc Thoi wards, O Mon district, Can Tho city
A5: SHIPPER | B5: : | C5: Doosan Enerbility Co., Ltd.
A6: ADDRESS | B6: : | C6: 22 DoosanVolvo-ro, Seongsan-gu, Chang-won-si, Gyeongsangnam-do 51711, Republic of Korea
A7: CONSIGNEE | B7: : | C7: Cty Doosan Enerbility Co.,Ltd HQ-Nha thau TH CV thuoc Goi thau so OM4-EPC-HHO-06 cho NMND O Mon IV Thoi Loi Area, Phuoc Thoi Ward, Can Tho City, Vietnam T : (+84) 367 566 167 F : (+84 243) 624 8485
A8: NOTIFY PARTY | B8: : | C8: Cty Doosan Enerbility Co.,Ltd HQ-Nha thau TH CV thuoc Goi thau so OM4-EPC-HHO-06 cho NMND O Mon IV Thoi Loi Area, Phươc Thoi Ward, Can Tho City, Vietnam T : (+84) 367 566 167 F : (+84 243) 624 8485 BRANCH OF KWANGJIN VIET NAM IN DUNG QUAT Co.,Ltd Dung Quat Economic Zone, Van Tuong Commune, Quang Ngai Province, Vietnam T : (+84) 28 3825 6330 Attn: Mr. Phuoc / Email: phuoc@kjtc.co.kr
A12: CONTRACT NO. | B12: : | C12: 06/2025/HĐ-PVN/OM4-06
A13: SHIPMENT NO. | B13: : | C13: OM4-DE-IS-0010
A14: EQUIPMENT DESCRIPTION | B14: : | C14: =[6]CI!B28 -> PLANT/ EQUIPMENT AND MATERIALS FOR O MON IV THERMAL
A15: DESCRIPTION OF GOODS | B15: : | C15: ='PL(2_2)'!D15 -> Zinc Primer Paint | L15: PL(2_2) Sheet 내 내용 반영 필요
A16: CONSIGNOR. | B16: : | C16: SAMSUNG E&L
A17: PACKAGE NO. | B17: : | C17: ='PL(2_2)'!C15 -> OM4-DE-IS-0010-001
A18: NET WEIGHT | B18: : | C18: ='PL(2_2)'!M15 -> 576 | D18: KG
A19: GROSS WEIGHT | B19: : | C19: ='PL(2_2)'!N15 -> 726 | D19: KG
A20: - MEASUREMENT | B20: : | C20: ='PL(2_2)'!I15 -> 120 | D20: cm(L) X | E20: ='PL(2_2)'!J15 -> 120 | F20: cm (W) X | G20: ='PL(2_2)'!K15 -> 110 | H20: cm (H) | I20: ='PL(2_2)'!L15 -> 1.584 | J20: CBM
A21: LOADING PORT | B21: : | C21: ='Packing List (1_2)'!B21 -> Busan International Port, Korea
A22: PORT OF DESTINATION | B22: : | C22: Ho Chi Minh City Port, Vietnam
A23: COUNTRY OF ORIGIN | B23: : | C23: Republic of Korea
A24: QUALITY | B24: : | C24: 100% BRAND NEW

Sheet SHIPPING MARK (2)
A1: SHIPPING MARK
A2: O MON IV THERMAL POWER PLANT
A3: =[6]CI!B26 -> Address: O Mon Power Complex at Phuoc Thoi wards, O Mon district, Can Tho city
A5: SHIPPER | B5: : | C5: Doosan Enerbility Co., Ltd.
A6: ADDRESS | B6: : | C6: 22 DoosanVolvo-ro, Seongsan-gu, Chang-won-si, Gyeongsangnam-do 51711, Republic of Korea
A7: CONSIGNEE | B7: : | C7: Cty Doosan Enerbility Co.,Ltd HQ-Nha thau TH CV thuoc Goi thau so OM4-EPC-HHO-06 cho NMND O Mon IV Thoi Loi Area, Phuoc Thoi Ward, Can Tho City, Vietnam T : (+84) 367 566 167 F : (+84 243) 624 8485
A8: NOTIFY PARTY | B8: : | C8: Cty Doosan Enerbility Co.,Ltd HQ-Nha thau TH CV thuoc Goi thau so OM4-EPC-HHO-06 cho NMND O Mon IV Thoi Loi Area, Phươc Thoi Ward, Can Tho City, Vietnam T : (+84) 367 566 167 F : (+84 243) 624 8485 BRANCH OF KWANGJIN VIET NAM IN DUNG QUAT Co.,Ltd Dung Quat Economic Zone, Van Tuong Commune, Quang Ngai Province, Vietnam T : (+84) 28 3825 6330 Attn: Mr. Phuoc / Email: phuoc@kjtc.co.kr
A12: CONTRACT NO. | B12: : | C12: 06/2025/HĐ-PVN/OM4-06
A13: SHIPMENT NO. | B13: : | C13: OM4-DE-IS-0010
A14: EQUIPMENT DESCRIPTION | B14: : | C14: =[6]CI!B28 -> PLANT/ EQUIPMENT AND MATERIALS FOR O MON IV THERMAL
A15: DESCRIPTION OF GOODS | B15: : | C15: ='PL(2_2)'!D16 -> Zinc Primer Paint, Sealant | L15: PL(2_2) Sheet 내 내용 반영 필요
A16: CONSIGNOR. | B16: : | C16: SAMSUNG E&L
A17: PACKAGE NO. | B17: : | C17: ='PL(2_2)'!C16 -> OM4-DE-IS-0010-002
A18: NET WEIGHT | B18: : | C18: ='PL(2_2)'!M16 -> 324 | D18: KG
A19: GROSS WEIGHT | B19: : | C19: ='PL(2_2)'!N16 -> 474 | D19: KG
A20: - MEASUREMENT | B20: : | C20: ='PL(2_2)'!I16 -> 120 | D20: cm(L) X | E20: ='PL(2_2)'!J16 -> 120 | F20: cm (W) X | G20: ='PL(2_2)'!K16 -> 110 | H20: cm (H) | I20: ='PL(2_2)'!L16 -> 1.584 | J20: CBM
A21: LOADING PORT | B21: : | C21: ='Packing List (1_2)'!B21 -> Busan International Port, Korea
A22: PORT OF DESTINATION | B22: : | C22: Ho Chi Minh City Port, Vietnam
A23: COUNTRY OF ORIGIN | B23: : | C23: Republic of Korea
A24: QUALITY | B24: : | C24: 100% BRAND NEW

Sheet Technical Description
A6: Technical Description
A7: Invoice no. | B7: ='Commercial Invoice'!H5 -> OM4-DE-IS-0010
A8: № | B8: Package No. | C8: Description of Goods | D8: Quantity | F8: Photo | H8: Technical specifications
D9: Nos | E9: Unit | F9: Before packing | G9: After packing
A10: 1 | B10: ='PL(2_2)'!C15 -> OM4-DE-IS-0010-001 | C10: ='PL(2_2)'!D15 -> Zinc Primer Paint | D10: ='PL(2_2)'!F15 -> 32 | E10: ='PL(2_2)'!G15 -> EA
A11: 2 | B11: ='PL(2_2)'!C16 -> OM4-DE-IS-0010-002 | C11: ='PL(2_2)'!D16 -> Zinc Primer Paint, Sealant | D11: ='PL(2_2)'!F16 -> 18 | E11: ='PL(2_2)'!G16 -> EA

Sheet CO

Sheet CQ

Sheet BL
I3: - In the B/L Form, "Freight Prepaid" must be used according to the signed EPC regulations, "Freight payable" cannot be used as the form we are drafting. - According to EPC, the Contractor is required to bear the risks and losses until handover, and must insure all goods during transportation, so remove the content of the complicated limitation regulations below in the B/L Form.

Sheet PSIC
