Workbook
Name _Hlk215568700: PSIC!$B$2
Name latent: #REF!
Name latent: '[4]steam table'!$N$5:$Q$102
Name tube_test_press1_12: #REF!

Sheet Detailed PL
C3: PECC2 Innovation Hub, 45 Street No.2, Truong Tho Ward, Thu Duc City, HCMC, Vietnam Tel: +84-28-2221 6468 | Fax: +84-28-2221 0408
B4: DETAILED PACKING LIST
C5: PL No. | D5: ='PL(2_2)'!D5 -> OM4-DE-IS-0011
C6: Dated | D6: ='PL(2_2)'!D6 -> 46181 | J6: * Storage Classification | O6: ** Plant/Equipment/Materials for
C7: Project | D7: ='PL(2_2)'!D7 -> O MON IV THERMAL POWER PLANT | J7: "A" | K7: : Indoor with Air conditioning | P7: HRSG | Q7: STG | R7: GTG | S7: BOP
C8: Referenced DWG No. | J8: "B" | K8: : Indoor without Air conditioning | O8: Unit 1 | P8: B1 | Q8: T1 | R8: G1 | S8: P2
J9: "C" | K9: : Hazardous Material | O9: Unit 2 | P9: B2 | Q9: T2 | R9: G2 | S9: P2
J10: "D" | K10: : Outdoor with waterproofing | O10: Common | P10: B0 | Q10: T0 | R10: G0 | S10: P0
J11: "E" | K11: : Outdoor without waterproofing
B13: SI. No. | C13: Package No. | D13: Description of Goods | F13: Manufacturer | G13: C/O of Goods | H13: Position in price schedule | I13: Quantity | K13: Package Type | L13: Measurement | P13: Net Weight (kg) | Q13: Gross Weight (kg) | R13: Hazardous Material | S13: Storage Classification (*) | T13: Tag No. | U13: Remark (**)
I14: Nos | J14: Unit | L14: Length (cm) | M14: Width (cm) | N14: Height (cm) | O14: Volume (cbm)
B15: 1 | C15: OM4-DE-IS-0011-001 | D15: Coupling for Steel Conduit | E15: 125mm (5") | F15: SAMSUNG E&L | G15: Republic of Korea | I15: 50 | J15: EA | P15: =W15*I15 -> 125 | W15: 2.5
B16: 2 | C16: =C15 -> OM4-DE-IS-0011-001 | D16: Flexible Conduit Connector (Male Type) | E16: 125mm (5") | F16: SAMSUNG E&L | G16: Republic of Korea | I16: 50 | J16: EA | P16: =W16*I16 -> 140 | W16: 2.8
B17: 3 | C17: =C16 -> OM4-DE-IS-0011-001 | D17: Flexible Conduit Connector (Female Type) | E17: 125mm (5") | F17: SAMSUNG E&L | G17: Republic of Korea | I17: 50 | J17: EA | P17: =W17*I17 -> 140 | W17: 2.8
B18: 4 | C18: =C17 -> OM4-DE-IS-0011-001 | D18: PIPE CLAMP With Bolt/Nut/Washer | E18: 125mm (5") | F18: SAMSUNG E&L | G18: Republic of Korea | I18: 500 | J18: SET | P18: =W18*I18 -> 500 | W18: 1
B19: 5 | C19: =C18 -> OM4-DE-IS-0011-001 | D19: Insulation Bushing W/Earthing | E19: 150mm (6") | F19: SAMSUNG E&L | G19: Republic of Korea | I19: 70 | J19: EA | P19: =W19*I19 -> 70 | W19: 1
B20: Sub-Total | I20: =SUM(I15:I19) -> 720 | K20: Wooden | L20: 150 | M20: 150 | N20: 100 | O20: =(L20*M20*N20)/10^6 -> 2.25 | P20: =SUM(P15:P19) -> 975 | Q20: =P20+300 -> 1275 | R20: N | S20: D | U20: P0
B21: 6 | C21: OM4-DE-IS-0011-002 | D21: Flexible Conduit (Water proof type) | E21: 125mm (5") | F21: SAMSUNG E&L | G21: Republic of Korea | I21: 120 | J21: M | P21: =W21*I21 -> 840 | W21: 7
B22: Sub-Total | I22: =SUM(I21) -> 120 | K22: Wooden | L22: 620 | M22: 100 | N22: 100 | O22: 6.14 | P22: =P21 -> 840 | Q22: =P22+300 -> 1140 | R22: N | S22: D | U22: P0
B23: Grand-Total | O23: =SUM(O15:O22) -> 8.39 | P23: =SUM(P20,P22) -> 1815 | Q23: =SUM(Q15:Q22) -> 2415

Sheet Commercial Invoice
B3: PECC2 Innovation Hub, 45 Street No.2, Truong Tho Ward, Thu Duc City, HCMC, Vietnam Tel: +84-28-2221 6468 | Fax: +84-28-2221 0408
A4: COMMERCIAL INVOICE
A5: SHIPPER: | G5: INVOICE NO. : | H5: OM4-DE-IS-0011
B6: Doosan Enerbility Co., Ltd. 22 DoosanVolvo-ro, Seongsan-gu, Chang-won-si, Gyeongsangnam-do 51711, Republic of Korea | G6: DATE: | H6: 46181
G7: CONTRACT NO. | H7: 06/2025/HĐ-PVN/OM4-06
G8: DATE: | H8: 45814
A9: CONSIGNEE : | G9: SHIPPING MARK
B10: Cty Doosan Enerbility Co.,Ltd HQ-Nha thau TH CV thuoc Goi thau so OM4-EPC-HHO-06 cho NMND O Mon IV Thoi Loi Area, Phuoc Thoi Ward, Can Tho City, Vietnam T : (+84) 367 566 167 F : (+84 243) 624 8485 | G10: O MON IV THERMAL POWER PLANT
A13: NOTIFY PARTY :
B14: Cty Doosan Enerbility Co.,Ltd HQ-Nha thau TH CV thuoc Goi thau so OM4-EPC-HHO-06 cho NMND O Mon IV Thoi Loi Area, Phươc Thoi Ward, Can Tho City, Vietnam T : (+84) 367 566 167 F : (+84 243) 624 8485 BRANCH OF KWANGJIN VIET NAM IN DUNG QUAT Co.,Ltd Dung Quat Economic Zone, Van Tuong Commune, Quang Ngai Province, Vietnam T : (+84) 28 3825 6330 Attn: Mr. Phuoc / Email: phuoc@kjtc.co.kr
G15: SHIPMENT NO. : | H15: =H5 -> OM4-DE-IS-0011
G17: TERM OF DELIVERY : | H17: CIF, Ho Chi Minh City Port, Vietnam
A18: VESSEL NAME : | C18: ETD :
B19: SAWASDEE SUNRISE 2608S | D19: 46208 | G19: QUALITY | H19: 100% BRAND NEW
A20: PORT OF LOADING : | C20: PORT OF DISCHARGE : | G20: PAYMENT TERMS: | H20: T/T
B21: Busan International Port, Korea | D21: Ho Chi Minh City Port, Vietnam
A22: BILL OF LADING/ AIRWAY BILL NO. : | C22: B/L DATE :
A24: FINAL DESTINATION :
B25: O MON IV THERMAL POWER PLANT
B26: Address: O Mon Power Complex at Phuoc Thoi wards, Can Tho city
A27: COMMODITY/DESCRIPTION OF GOODS | H27: UNIT | I27: QUANTITY | J27: UNIT PRICE (USD) | K27: AMOUNT (USD)
B28: PLANT/ EQUIPMENT AND MATERIALS FOR O MON IV THERMAL POWER PLANT (Contract No. OM4-PO-DE-001)
B29: Conduit & Accessories included I&C Conduit (Steel Conduit) | H29: EA | I29: =SUM('Packing List (1_2)'!H30:H36) -> 840 | J29: =ROUND(K29/I29,2) -> 45.09 | K29: ='Break Down CI'!N15 -> 37873.86
B33: Number of packages: | D33: 2 | E33: PKGS | M33: Freight | N33: 1277
M34: Insurance | N34: =K29*110%*0.1045% -> 43.536002
B38: TOTAL AMOUNT AT THIS SHIPMENT : | K38: =SUM(K29:K33) -> 37873.86
G45: Signed by
H46: Jinho. Lee / Deputy Project Director

Sheet Break Down CI
B5: ='Commercial Invoice'!G5 -> INVOICE NO. : | C5: ='Commercial Invoice'!H5 -> OM4-DE-IS-0011 | M5: DATE : | O5: ='Commercial Invoice'!H6 -> 46181
A7: SI. No. | B7: Package No. | C7: COMMODITY/DESCRIPTION OF GOODS | E7: C/O of Goods | F7: POSITION IN THE MASTER LIST | G7: POSITION IN PRICE SCHEDULE | H7: Quantity | J7: Package Type | K7: NET WEIGHT (KG) | L7: GROSS WEIGHT (KG) | M7: UNIT PRICE (USD) | N7: AMOUNT (USD) | O7: Remark (**)
H8: Nos | I8: Unit | Q8: HS CODE
A9: 1 | B9: OM4-DE-IS-0011-001 | C9: Coupling for Steel Conduit | D9: 125mm (5") | E9: Republic of Korea | F9: N/A | G9: PS 1.1, Ⅴ, 11 | H9: ='Detailed PL'!I15 -> 50 | I9: EA | J9: Wooden | K9: ='Detailed PL'!P15 -> 125 | L9: 146 | M9: 22.86 | N9: 1143 | O9: P0 | Q9: 7307.92-9000 | S9: =H9*M9 -> 1143 | U9: 1143.39
A10: 2 | B10: OM4-DE-IS-0011-001 | C10: Flexible Conduit Connector (Male Type) | D10: 125mm (5") | E10: Republic of Korea | F10: N/A | G10: PS 1.1, Ⅴ, 11 | H10: ='Detailed PL'!I16 -> 50 | I10: EA | J10: Wooden | K10: ='Detailed PL'!P16 -> 140 | L10: 160 | M10: 104.91 | N10: 5245.5 | O10: P0 | Q10: 7907.00-2020 | S10: =H10*M10 -> 5245.5 | U10: 5245.81
A11: 3 | B11: OM4-DE-IS-0011-001 | C11: Flexible Conduit Connector (Female Type) | D11: 125mm (5") | E11: Republic of Korea | F11: N/A | G11: PS 1.1, Ⅴ, 11 | H11: ='Detailed PL'!I17 -> 50 | I11: EA | J11: Wooden | K11: ='Detailed PL'!P17 -> 140 | L11: 160 | M11: 114.89 | N11: 5744.5 | O11: P0 | Q11: 7907.00-2020 | S11: =H11*M11 -> 5744.5 | U11: 5745.21
A12: 4 | B12: OM4-DE-IS-0011-001 | C12: PIPE CLAMP With Bolt/Nut/Washer | D12: 125mm (5") | E12: Republic of Korea | F12: N/A | G12: PS 1.1, Ⅴ, 11 | H12: ='Detailed PL'!I18 -> 500 | I12: SET | J12: Wooden | K12: ='Detailed PL'!P18 -> 500 | L12: 710 | M12: 6.3 | N12: 3150 | O12: P0 | Q12: 7326.90-9000 | S12: =H12*M12 -> 3150 | U12: 3149.31
A13: 5 | B13: OM4-DE-IS-0011-001 | C13: Insulation Bushing W/Earthing | D13: 150mm (6") | E13: Republic of Korea | F13: N/A | G13: PS 1.1, Ⅴ, 11 | H13: ='Detailed PL'!I19 -> 70 | I13: EA | J13: Wooden | K13: ='Detailed PL'!P19 -> 70 | L13: 99 | M13: 26.91 | N13: 1883.66 | O13: P0 | Q13: 7907.00-9090 | S13: =H13*M13 -> 1883.7 | U13: 1883.44
A14: 6 | B14: OM4-DE-IS-0011-002 | C14: Flexible Conduit (Water proof type) | D14: 125mm (5") | E14: Republic of Korea | F14: N/A | G14: PS 1.1, Ⅴ, 11 | H14: ='Detailed PL'!I21 -> 120 | I14: M | J14: Wooden | K14: ='Detailed PL'!P21 -> 840 | L14: 1140 | M14: 172.56 | N14: 20707.2 | O14: P0 | Q14: 8307.10-0000 | S14: =H14*M14 -> 20707.2 | U14: 20706.69
J15: TOTAL AMOUNT AT THIS SHIPMENT | N15: =SUM(N9:N14) -> 37873.86 | U15: 37873.86

Sheet Packing List (1_2)
B3: PECC2 Innovation Hub, 45 Street No.2, Truong Tho Ward, Thu Duc City, HCMC, Vietnam Tel: +84-28-2221 6468 | Fax: +84-28-2221 0408
A4: PACKING LIST(1/2)
A5: SHIPPER: | G5: P/L No. | H5: OM4-DE-IS-0011
B6: Doosan Enerbility Co., Ltd. 22 DoosanVolvo-ro, Seongsan-gu, Chang-won-si, Gyeongsangnam-do 51711, Republic of Korea | G6: DATE: | H6: ='Commercial Invoice'!H6 -> 46181
G7: CONTRACT NO. | H7: 06/2025/HĐ-PVN/OM4-06
G8: DATE: | H8: ='Commercial Invoice'!H8 -> 45814
A9: CONSIGNEE : | G9: =[6]CI!G9 -> SHIPPING MARK
B10: Cty Doosan Enerbility Co.,Ltd HQ-Nha thau TH CV thuoc Goi thau so OM4-EPC-HHO-06 cho NMND O Mon IV Thoi Loi Area, Phuoc Thoi Ward, Can Tho City, Vietnam T : (+84) 367 566 167 F : (+84 243) 624 8485 | G10: O MON IV THERMAL POWER PLANT
A13: NOTIFY PARTY :
B14: Cty Doosan Enerbility Co.,Ltd HQ-Nha thau TH CV thuoc Goi thau so OM4-EPC-HHO-06 cho NMND O Mon IV Thoi Loi Area, Phươc Thoi Ward, Can Tho City, Vietnam T : (+84) 367 566 167 F : (+84 243) 624 8485 BRANCH OF KWANGJIN VIET NAM IN DUNG QUAT Co.,Ltd Dung Quat Economic Zone, Van Tuong Commune, Quang Ngai Province, Vietnam T : (+84) 28 3825 6330 Attn: Mr. Phuoc / Email: phuoc@kjtc.co.kr
G15: SHIPMENT NO. : | H15: =H5 -> OM4-DE-IS-0011
G17: TERM OF DELIVERY : | H17: CIF, Ho Chi Minh City Port, Vietnam
A18: VESSEL NAME : | C18: ETD :
B19: SAWASDEE SUNRISE 2608S | D19: 46208 | G19: QUALITY | H19: 100% BRAND NEW
A20: PORT OF LOADING : | C20: PORT OF DISCHARGE :
B21: Busan International Port, Korea | D21: Ho Chi Minh City Port, Vietnam
A22: BILL OF LADING/ AIRWAY BILL NO. : | C22: B/L DATE :
A24: FINAL DESTINATION :
B25: O MON IV THERMAL POWER PLANT
B26: Address: O Mon Power Complex at Phuoc Thoi wards, Can Tho city
A27: COMMODITY/DESCRIPTION OF GOODS | G27: UNIT | H27: QUANTITY | I27: NET WEIGHT (KG) | J27: GROSS WEIGHT (KG) | K27: MEASUREMENT (CBM)
B28: PLANT/ EQUIPMENT AND MATERIALS FOR O MON IV THERMAL POWER PLANT (Contract No. OM4-PO-DE-001)
A29: Conduit & Accessories included I&C Conduit (Steel Conduit)
G30: EA | H30: ='PL(2_2)'!F15 -> 720 | I30: ='PL(2_2)'!M15 -> 975 | J30: ='PL(2_2)'!N15 -> 1275 | K30: ='PL(2_2)'!L15 -> 2.25
G31: EA | H31: ='PL(2_2)'!F16 -> 120 | I31: ='PL(2_2)'!M16 -> 840 | J31: ='PL(2_2)'!N16 -> 1140 | K31: ='PL(2_2)'!L16 -> 6.14
B34: Number of packages: | D34: 2 | E34: PKGS
G38: TOTAL | I38: =SUM(I28:I37) -> 1815 | J38: =SUM(J28:J37) -> 2415 | K38: =SUM(K28:K37) -> 8.39
G46: Signed by
H47: Jinho. Lee / Deputy Project Director

Sheet PL(2_2)
C3: PECC2 Innovation Hub, 45 Street No.2, Truong Tho Ward, Thu Duc City, HCMC, Vietnam Tel: +84-28-2221 6468 | Fax: +84-28-2221 0408
B4: PACKING LIST(2/2)
C5: P/L No. | D5: ='Packing List (1_2)'!H5 -> OM4-DE-IS-0011
C6: Dated | D6: ='Packing List (1_2)'!H6 -> 46181 | I6: * Storage Classification | N6: ** Plant/Equipment/Materials for
C7: Project | D7: O MON IV THERMAL POWER PLANT | I7: "A" | J7: : Indoor with Air conditioning | O7: HRSG | P7: STG | Q7: GTG | R7: BOP
I8: "B" | J8: : Indoor without Air conditioning | N8: Unit 1 | O8: B1 | P8: T1 | Q8: G1 | R8: P2
I9: "C" | J9: : Hazardous Material | N9: Unit 2 | O9: B2 | P9: T2 | Q9: G2 | R9: P2
I10: "D" | J10: : Outdoor with waterproofing | N10: Common | O10: B0 | P10: T0 | Q10: G0 | R10: P0
I11: "E" | J11: : Outdoor without waterproofing
B13: SI. No. | C13: Package No. | D13: Description of Goods | E13: Position in price schedule | F13: Quantity | H13: Package Type | I13: Measurement | M13: Net Weight (kg) | N13: Gross Weight (kg) | O13: Hazardous Material | P13: COG Marked (Y/N) | Q13: Sling Point Marked (Y/N) | R13: Handle with care Marked (Y/N) | S13: Storage Classification (*) | T13: Remark (**)
F14: Nos | G14: Unit | I14: Length (cm) | J14: Width (cm) | K14: Height (cm) | L14: Volume (cbm)
B15: 1 | C15: ='Detailed PL'!C15 -> OM4-DE-IS-0011-001 | D15: Conduit Fittings | F15: ='Detailed PL'!I20 -> 720 | G15: EA | H15: ='Detailed PL'!K20 -> Wooden | I15: ='Detailed PL'!L20 -> 150 | J15: ='Detailed PL'!M20 -> 150 | K15: ='Detailed PL'!N20 -> 100 | L15: ='Detailed PL'!O20 -> 2.25 | M15: ='Detailed PL'!P20 -> 975 | N15: ='Detailed PL'!Q20 -> 1275 | O15: N | P15: Y | Q15: Y | R15: N | S15: D | T15: P0
B16: 2 | C16: ='Detailed PL'!C21 -> OM4-DE-IS-0011-002 | D16: Flexible Conduit | F16: ='Detailed PL'!I22 -> 120 | G16: EA | H16: ='Detailed PL'!K22 -> Wooden | I16: ='Detailed PL'!L22 -> 620 | J16: ='Detailed PL'!M22 -> 100 | K16: ='Detailed PL'!N22 -> 100 | L16: 6.14 | M16: ='Detailed PL'!P22 -> 840 | N16: ='Detailed PL'!Q22 -> 1140 | O16: N | P16: Y | Q16: Y | R16: N | S16: D | T16: P0
B17: Grand Total | L17: =SUM(L15:L16) -> 8.39 | M17: =SUM(M15:M16) -> 1815 | N17: =SUM(N15:N16) -> 2415

Sheet SHIPPING MARK (1)
A1: SHIPPING MARK
A2: O MON IV THERMAL POWER PLANT
A3: =[6]CI!B26 -> Address: O Mon Power Complex at Phuoc Thoi wards, O Mon district, Can Tho city
A5: SHIPPER | B5: : | C5: Doosan Enerbility Co., Ltd.
A6: ADDRESS | B6: : | C6: 22 DoosanVolvo-ro, Seongsan-gu, Chang-won-si, Gyeongsangnam-do 51711, Republic of Korea
A7: CONSIGNEE | B7: : | C7: Cty Doosan Enerbility Co.,Ltd HQ-Nha thau TH CV thuoc Goi thau so OM4-EPC-HHO-06 cho NMND O Mon IV Thoi Loi Area, Phuoc Thoi Ward, Can Tho City, Vietnam T : (+84) 367 566 167 F : (+84 243) 624 8485
A8: NOTIFY PARTY | B8: : | C8: Cty Doosan Enerbility Co.,Ltd HQ-Nha thau TH CV thuoc Goi thau so OM4-EPC-HHO-06 cho NMND O Mon IV Thoi Loi Area, Phươc Thoi Ward, Can Tho City, Vietnam T : (+84) 367 566 167 F : (+84 243) 624 8485 BRANCH OF KWANGJIN VIET NAM IN DUNG QUAT Co.,Ltd Dung Quat Economic Zone, Van Tuong Commune, Quang Ngai Province, Vietnam T : (+84) 28 3825 6330 Attn: Mr. Phuoc / Email: phuoc@kjtc.co.kr
A12: CONTRACT NO. | B12: : | C12: 06/2025/HĐ-PVN/OM4-06
A13: SHIPMENT NO. | B13: : | C13: OM4-DE-IS-0011
A14: EQUIPMENT DESCRIPTION | B14: : | C14: =[6]CI!B28 -> PLANT/ EQUIPMENT AND MATERIALS FOR O MON IV THERMAL
A15: DESCRIPTION OF GOODS | B15: : | C15: ='PL(2_2)'!D15 -> Conduit Fittings
A16: CONSIGNOR. | B16: : | C16: SAMSUNG E&L
A17: PACKAGE NO. | B17: : | C17: ='PL(2_2)'!C15 -> OM4-DE-IS-0011-001
A18: NET WEIGHT | B18: : | C18: ='PL(2_2)'!M15 -> 975 | D18: KG
A19: GROSS WEIGHT | B19: : | C19: ='PL(2_2)'!N15 -> 1275 | D19: KG
A20: - MEASUREMENT | B20: : | C20: ='PL(2_2)'!I15 -> 150 | D20: cm(L) X | E20: ='PL(2_2)'!J15 -> 150 | F20: cm (W) X | G20: ='PL(2_2)'!K15 -> 100 | H20: cm (H) | I20: ='PL(2_2)'!L15 -> 2.25 | J20: CBM
A21: LOADING PORT | B21: : | C21: ='Packing List (1_2)'!B21 -> Busan International Port, Korea
A22: PORT OF DESTINATION | B22: : | C22: Ho Chi Minh City Port, Vietnam
A23: COUNTRY OF ORIGIN | B23: : | C23: Republic of Korea
A24: QUALITY | B24: : | C24: 100% BRAND NEW

Sheet SHIPPING MARK (2)
A1: SHIPPING MARK
A2: O MON IV THERMAL POWER PLANT
A3: =[6]CI!B26 -> Address: O Mon Power Complex at Phuoc Thoi wards, O Mon district, Can Tho city
A5: SHIPPER | B5: : | C5: Doosan Enerbility Co., Ltd.
A6: ADDRESS | B6: : | C6: 22 DoosanVolvo-ro, Seongsan-gu, Chang-won-si, Gyeongsangnam-do 51711, Republic of Korea
A7: CONSIGNEE | B7: : | C7: Cty Doosan Enerbility Co.,Ltd HQ-Nha thau TH CV thuoc Goi thau so OM4-EPC-HHO-06 cho NMND O Mon IV Thoi Loi Area, Phuoc Thoi Ward, Can Tho City, Vietnam T : (+84) 367 566 167 F : (+84 243) 624 8485
A8: NOTIFY PARTY | B8: : | C8: Cty Doosan Enerbility Co.,Ltd HQ-Nha thau TH CV thuoc Goi thau so OM4-EPC-HHO-06 cho NMND O Mon IV Thoi Loi Area, Phươc Thoi Ward, Can Tho City, Vietnam T : (+84) 367 566 167 F : (+84 243) 624 8485 BRANCH OF KWANGJIN VIET NAM IN DUNG QUAT Co.,Ltd Dung Quat Economic Zone, Van Tuong Commune, Quang Ngai Province, Vietnam T : (+84) 28 3825 6330 Attn: Mr. Phuoc / Email: phuoc@kjtc.co.kr
A12: CONTRACT NO. | B12: : | C12: 06/2025/HĐ-PVN/OM4-06
A13: SHIPMENT NO. | B13: : | C13: OM4-DE-IS-0011
A14: EQUIPMENT DESCRIPTION | B14: : | C14: =[6]CI!B28 -> PLANT/ EQUIPMENT AND MATERIALS FOR O MON IV THERMAL
A15: DESCRIPTION OF GOODS | B15: : | C15: ='PL(2_2)'!D16 -> Flexible Conduit
A16: CONSIGNOR. | B16: : | C16: SAMSUNG E&L
A17: PACKAGE NO. | B17: : | C17: ='PL(2_2)'!C16 -> OM4-DE-IS-0011-002
A18: NET WEIGHT | B18: : | C18: ='PL(2_2)'!M16 -> 840 | D18: KG
A19: GROSS WEIGHT | B19: : | C19: ='PL(2_2)'!N16 -> 1140 | D19: KG
A20: - MEASUREMENT | B20: : | C20: ='PL(2_2)'!I16 -> 620 | D20: cm(L) X | E20: ='PL(2_2)'!J16 -> 100 | F20: cm (W) X | G20: ='PL(2_2)'!K16 -> 100 | H20: cm (H) | I20: ='PL(2_2)'!L16 -> 6.14 | J20: CBM
A21: LOADING PORT | B21: : | C21: ='Packing List (1_2)'!B21 -> Busan International Port, Korea
A22: PORT OF DESTINATION | B22: : | C22: Ho Chi Minh City Port, Vietnam
A23: COUNTRY OF ORIGIN | B23: : | C23: Republic of Korea
A24: QUALITY | B24: : | C24: 100% BRAND NEW

Sheet Technical Description
A6: Technical Description
A7: Invoice no. | B7: ='Commercial Invoice'!H5 -> OM4-DE-IS-0011
A8: № | B8: Package No. | C8: Description of Goods | D8: Quantity | F8: Photo | H8: Technical specifications
D9: Nos | E9: Unit | F9: Before packing | G9: After packing
A10: 1 | B10: ='PL(2_2)'!C15 -> OM4-DE-IS-0011-001 | C10: ='PL(2_2)'!D15 -> Conduit Fittings | D10: ='PL(2_2)'!F15 -> 720 | E10: ='PL(2_2)'!G15 -> EA
A11: 2 | B11: ='PL(2_2)'!C16 -> OM4-DE-IS-0011-002 | C11: ='PL(2_2)'!D16 -> Flexible Conduit | D11: ='PL(2_2)'!F16 -> 120 | E11: ='PL(2_2)'!G16 -> EA

Sheet CO

Sheet CQ

Sheet BL
I3: - In the B/L Form, "Freight Prepaid" must be used according to the signed EPC regulations, "Freight payable" cannot be used as the form we are drafting. - According to EPC, the Contractor is required to bear the risks and losses until handover, and must insure all goods during transportation, so remove the content of the complicated limitation regulations below in the B/L Form.

Sheet PSIC
